AUTHORS.rst
LICENSE.rst
MANIFEST.in
README.rst
setup.py
django_shop_paypal.egg-info/PKG-INFO
django_shop_paypal.egg-info/SOURCES.txt
django_shop_paypal.egg-info/dependency_links.txt
django_shop_paypal.egg-info/not-zip-safe
django_shop_paypal.egg-info/requires.txt
django_shop_paypal.egg-info/top_level.txt
shop_paypal/__init__.py
shop_paypal/models.py
shop_paypal/offsite_paypal.py
shop_paypal/templates/shop_paypal/payment.html
shop_paypal/templates/shop_paypal/success.html