Metadata-Version: 1.0
Name: django-shop-paypal
Version: 0.0.1
Summary: An paypal payment backend wrapping django-paypal
Home-page: http://www.django-shop.org/
Author: Christopher Glass
Author-email: tribaal@gmail.com
License: BSD License
Platform: OS Independent
